llmdocparser/__init__.py
llmdocparser/example/attention_is_all_you_need.pdf
llmdocparser/llm_chain/__init__.py
llmdocparser/llm_chain/llm_factory.py
llmdocparser/llm_chain/llm_inference.py
llmdocparser/llm_parser.py
llmdocparser/parser/__init__.py
llmdocparser/parser/layout_parser.py
llmdocparser/parser/rect_merge.py
llmdocparser-0.1.6.1.dist-info/LICENSE
llmdocparser-0.1.6.1.dist-info/METADATA
llmdocparser-0.1.6.1.dist-info/WHEEL
llmdocparser-0.1.6.1.dist-info/RECORD
